CHANGES.rst
CONTRIBUTORS.rst
DEVELOP.rst
LICENSE.GPL
LICENSE.rst
MANIFEST.in
README.rst
setup.cfg
setup.py
docs/conf.py
docs/index.rst
src/collective/__init__.py
src/collective.cleanuprevisions.egg-info/PKG-INFO
src/collective.cleanuprevisions.egg-info/SOURCES.txt
src/collective.cleanuprevisions.egg-info/dependency_links.txt
src/collective.cleanuprevisions.egg-info/entry_points.txt
src/collective.cleanuprevisions.egg-info/namespace_packages.txt
src/collective.cleanuprevisions.egg-info/not-zip-safe
src/collective.cleanuprevisions.egg-info/requires.txt
src/collective.cleanuprevisions.egg-info/top_level.txt
src/collective/cleanuprevisions/__init__.py
src/collective/cleanuprevisions/configure.zcml
src/collective/cleanuprevisions/interfaces.py
src/collective/cleanuprevisions/permissions.zcml
src/collective/cleanuprevisions/setuphandlers.py
src/collective/cleanuprevisions/testing.py
src/collective/cleanuprevisions/browser/__init__.py
src/collective/cleanuprevisions/browser/configure.zcml
src/collective/cleanuprevisions/browser/overrides/.gitkeep
src/collective/cleanuprevisions/browser/static/.gitkeep
src/collective/cleanuprevisions/locales/README.rst
src/collective/cleanuprevisions/locales/__init__.py
src/collective/cleanuprevisions/locales/collective.cleanuprevisions.pot
src/collective/cleanuprevisions/locales/update.py
src/collective/cleanuprevisions/locales/update.sh
src/collective/cleanuprevisions/locales/en/LC_MESSAGES/collective.cleanuprevisions.po
src/collective/cleanuprevisions/profiles/default/browserlayer.xml
src/collective/cleanuprevisions/profiles/default/catalog.xml
src/collective/cleanuprevisions/profiles/default/metadata.xml
src/collective/cleanuprevisions/profiles/default/rolemap.xml
src/collective/cleanuprevisions/profiles/default/registry/main.xml
src/collective/cleanuprevisions/profiles/uninstall/browserlayer.xml
src/collective/cleanuprevisions/tests/__init__.py
src/collective/cleanuprevisions/tests/test_robot.py
src/collective/cleanuprevisions/tests/test_setup.py
src/collective/cleanuprevisions/tests/test_view_clean_revisions.py
src/collective/cleanuprevisions/tests/robot/test_example.robot
src/collective/cleanuprevisions/views/__init__.py
src/collective/cleanuprevisions/views/clean_revisions.py
src/collective/cleanuprevisions/views/configure.zcml